gettsim/__init__.py
gettsim/_version.py
gettsim/germany/__init__.py
gettsim/germany/hh_characteristics.py
gettsim/germany/ids.py
gettsim/germany/individual_characteristics.py
gettsim/germany/inputs.py
gettsim/germany/param_types.py
gettsim/germany/arbeitslosengeld_2/__init__.py
gettsim/germany/arbeitslosengeld_2/arbeitslosengeld_2.py
gettsim/germany/arbeitslosengeld_2/bedarfe.yaml
gettsim/germany/arbeitslosengeld_2/einkommen.py
gettsim/germany/arbeitslosengeld_2/freibeträge.yaml
gettsim/germany/arbeitslosengeld_2/freibeträge_vermögen.py
gettsim/germany/arbeitslosengeld_2/inputs.py
gettsim/germany/arbeitslosengeld_2/kindergeldübertrag.py
gettsim/germany/arbeitslosengeld_2/kosten_der_unterkunft.yaml
gettsim/germany/arbeitslosengeld_2/regelbedarf.py
gettsim/germany/bürgergeld/__init__.py
gettsim/germany/bürgergeld/bedarfe.yaml
gettsim/germany/bürgergeld/bürgergeld.py
gettsim/germany/bürgergeld/einkommen.py
gettsim/germany/bürgergeld/freibeträge.yaml
gettsim/germany/bürgergeld/freibeträge_vermögen.py
gettsim/germany/bürgergeld/inputs.py
gettsim/germany/bürgergeld/kindergeldübertrag.py
gettsim/germany/bürgergeld/kosten_der_unterkunft.yaml
gettsim/germany/bürgergeld/regelbedarf.py
gettsim/germany/einkommensteuer/__init__.py
gettsim/germany/einkommensteuer/einkommen.py
gettsim/germany/einkommensteuer/einkommensteuer.py
gettsim/germany/einkommensteuer/einkommensteuertarif.yaml
gettsim/germany/einkommensteuer/inputs.py
gettsim/germany/einkommensteuer/kinderfreibetrag.py
gettsim/germany/einkommensteuer/kinderfreibetrag.yaml
gettsim/germany/einkommensteuer/zu_versteuerndes_einkommen.py
gettsim/germany/einkommensteuer/abgeltungssteuer/__init__.py
gettsim/germany/einkommensteuer/abgeltungssteuer/abgeltungssteuer.py
gettsim/germany/einkommensteuer/abgeltungssteuer/abgeltungssteuer.yaml
gettsim/germany/einkommensteuer/abzüge/__init__.py
gettsim/germany/einkommensteuer/abzüge/alleinerziehend.py
gettsim/germany/einkommensteuer/abzüge/alleinerziehend.yaml
gettsim-1.0.dist-info/METADATA
gettsim-1.0.dist-info/WHEEL
gettsim-1.0.dist-info/licenses/LICENSE
gettsim-1.0.dist-info/RECORD
