Metadata-Version: 2.4
Name: gettsim
Version: 1.0
Summary: The German Taxes and Transfers SIMulator
Project-URL: Repository, https://github.com/ttsim-dev/gettsim
Project-URL: Changelog, https://gettsim.readthedocs.io/en/stable/changes.html
Project-URL: Documentation, https://gettsim.readthedocs.io
Project-URL: Github, https://github.com/ttsim-dev/gettsim
Project-URL: Tracker, https://github.com/ttsim-dev/gettsim/issues
Author: Marvin Immesberger, Christian Zimpelmann
Author-email: Hans-Martin von Gaudecker <hmgaudecker@uni-bonn.de>
Maintainer: Marvin Immesberger
Maintainer-email: Hans-Martin von Gaudecker <hmgaudecker@uni-bonn.de>
License:                     GNU AFFERO GENERAL PUBLIC LICENSE
License-File: LICENSE
Keywords: Benefits,Economics,Germany,Pensions,Taxes,Transfers
Classifier: Intended Audience :: Science/Research
Classifier: License :: OSI Approved :: GNU Affero General Public License v3
Classifier: License :: OSI Approved :: GNU General Public License v3 (GPLv3)
Classifier: Operating System :: MacOS :: MacOS X
Classifier: Operating System :: Microsoft :: Windows
Classifier: Operating System :: POSIX
Classifier: Operating System :: Unix
Classifier: Programming Language :: Python :: 3
Classifier: Programming Language :: Python :: 3 :: Only
Requires-Python: >=3.11
Requires-Dist: ttsim-backend>=1.1.0
